{"nodes": [{"id": "c_users_nitin_mishra_workspace_01_development_active_cine_stream_platform_main_zip_public_js_browse_js", "label": "browse.js", "file_type": "code", "source_file": "C:\\Users\\NITIN MISHRA\\Workspace\\01_Development\\Active\\cine-stream-platform-main.zip\\public\\js\\browse.js", "source_location": "L1"}, {"id": "js_browse_valid_categories", "label": "VALID_CATEGORIES", "file_type": "code", "source_file": "C:\\Users\\NITIN MISHRA\\Workspace\\01_Development\\Active\\cine-stream-platform-main.zip\\public\\js\\browse.js", "source_location": "L23"}, {"id": "js_browse_category_meta", "label": "CATEGORY_META", "file_type": "code", "source_file": "C:\\Users\\NITIN MISHRA\\Workspace\\01_Development\\Active\\cine-stream-platform-main.zip\\public\\js\\browse.js", "source_location": "L29"}, {"id": "js_browse_items", "label": "_items", "file_type": "code", "source_file": "C:\\Users\\NITIN MISHRA\\Workspace\\01_Development\\Active\\cine-stream-platform-main.zip\\public\\js\\browse.js", "source_location": "L69"}, {"id": "js_browse_filters", "label": "_filters", "file_type": "code", "source_file": "C:\\Users\\NITIN MISHRA\\Workspace\\01_Development\\Active\\cine-stream-platform-main.zip\\public\\js\\browse.js", "source_location": "L74"}, {"id": "js_browse_init", "label": "init()", "file_type": "code", "source_file": "C:\\Users\\NITIN MISHRA\\Workspace\\01_Development\\Active\\cine-stream-platform-main.zip\\public\\js\\browse.js", "source_location": "L88"}, {"id": "js_browse_detectcategoryfrompath", "label": "detectCategoryFromPath()", "file_type": "code", "source_file": "C:\\Users\\NITIN MISHRA\\Workspace\\01_Development\\Active\\cine-stream-platform-main.zip\\public\\js\\browse.js", "source_location": "L120"}, {"id": "js_browse_renderbreadcrumb", "label": "renderBreadcrumb()", "file_type": "code", "source_file": "C:\\Users\\NITIN MISHRA\\Workspace\\01_Development\\Active\\cine-stream-platform-main.zip\\public\\js\\browse.js", "source_location": "L126"}, {"id": "js_browse_renderhero", "label": "renderHero()", "file_type": "code", "source_file": "C:\\Users\\NITIN MISHRA\\Workspace\\01_Development\\Active\\cine-stream-platform-main.zip\\public\\js\\browse.js", "source_location": "L134"}, {"id": "js_browse_setupcategoryspecificui", "label": "setupCategorySpecificUI()", "file_type": "code", "source_file": "C:\\Users\\NITIN MISHRA\\Workspace\\01_Development\\Active\\cine-stream-platform-main.zip\\public\\js\\browse.js", "source_location": "L153"}, {"id": "js_browse_loadinitialpage", "label": "loadInitialPage()", "file_type": "code", "source_file": "C:\\Users\\NITIN MISHRA\\Workspace\\01_Development\\Active\\cine-stream-platform-main.zip\\public\\js\\browse.js", "source_location": "L161"}, {"id": "js_browse_buildquerystring", "label": "buildQueryString()", "file_type": "code", "source_file": "C:\\Users\\NITIN MISHRA\\Workspace\\01_Development\\Active\\cine-stream-platform-main.zip\\public\\js\\browse.js", "source_location": "L191"}, {"id": "js_browse_fetchpage", "label": "fetchPage()", "file_type": "code", "source_file": "C:\\Users\\NITIN MISHRA\\Workspace\\01_Development\\Active\\cine-stream-platform-main.zip\\public\\js\\browse.js", "source_location": "L208"}, {"id": "js_browse_renderitems", "label": "renderItems()", "file_type": "code", "source_file": "C:\\Users\\NITIN MISHRA\\Workspace\\01_Development\\Active\\cine-stream-platform-main.zip\\public\\js\\browse.js", "source_location": "L265"}, {"id": "js_browse_isplayableitem", "label": "_isPlayableItem()", "file_type": "code", "source_file": "C:\\Users\\NITIN MISHRA\\Workspace\\01_Development\\Active\\cine-stream-platform-main.zip\\public\\js\\browse.js", "source_location": "L313"}, {"id": "js_browse_hasposter", "label": "_hasPoster()", "file_type": "code", "source_file": "C:\\Users\\NITIN MISHRA\\Workspace\\01_Development\\Active\\cine-stream-platform-main.zip\\public\\js\\browse.js", "source_location": "L324"}, {"id": "js_browse_showloading", "label": "showLoading()", "file_type": "code", "source_file": "C:\\Users\\NITIN MISHRA\\Workspace\\01_Development\\Active\\cine-stream-platform-main.zip\\public\\js\\browse.js", "source_location": "L329"}, {"id": "js_browse_hideloading", "label": "hideLoading()", "file_type": "code", "source_file": "C:\\Users\\NITIN MISHRA\\Workspace\\01_Development\\Active\\cine-stream-platform-main.zip\\public\\js\\browse.js", "source_location": "L336"}, {"id": "js_browse_showend", "label": "showEnd()", "file_type": "code", "source_file": "C:\\Users\\NITIN MISHRA\\Workspace\\01_Development\\Active\\cine-stream-platform-main.zip\\public\\js\\browse.js", "source_location": "L341"}, {"id": "js_browse_setupinfinitescroll", "label": "setupInfiniteScroll()", "file_type": "code", "source_file": "C:\\Users\\NITIN MISHRA\\Workspace\\01_Development\\Active\\cine-stream-platform-main.zip\\public\\js\\browse.js", "source_location": "L351"}, {"id": "js_browse_teardowninfinitescroll", "label": "teardownInfiniteScroll()", "file_type": "code", "source_file": "C:\\Users\\NITIN MISHRA\\Workspace\\01_Development\\Active\\cine-stream-platform-main.zip\\public\\js\\browse.js", "source_location": "L376"}, {"id": "js_browse_showretrybutton", "label": "showRetryButton()", "file_type": "code", "source_file": "C:\\Users\\NITIN MISHRA\\Workspace\\01_Development\\Active\\cine-stream-platform-main.zip\\public\\js\\browse.js", "source_location": "L388"}, {"id": "js_browse_common_genres", "label": "COMMON_GENRES", "file_type": "code", "source_file": "C:\\Users\\NITIN MISHRA\\Workspace\\01_Development\\Active\\cine-stream-platform-main.zip\\public\\js\\browse.js", "source_location": "L435"}, {"id": "js_browse_populategenrecheckboxes", "label": "populateGenreCheckboxes()", "file_type": "code", "source_file": "C:\\Users\\NITIN MISHRA\\Workspace\\01_Development\\Active\\cine-stream-platform-main.zip\\public\\js\\browse.js", "source_location": "L446"}, {"id": "js_browse_readfiltersfromform", "label": "readFiltersFromForm()", "file_type": "code", "source_file": "C:\\Users\\NITIN MISHRA\\Workspace\\01_Development\\Active\\cine-stream-platform-main.zip\\public\\js\\browse.js", "source_location": "L458"}, {"id": "js_browse_applyfilters", "label": "applyFilters()", "file_type": "code", "source_file": "C:\\Users\\NITIN MISHRA\\Workspace\\01_Development\\Active\\cine-stream-platform-main.zip\\public\\js\\browse.js", "source_location": "L503"}, {"id": "js_browse_clearallfilters", "label": "clearAllFilters()", "file_type": "code", "source_file": "C:\\Users\\NITIN MISHRA\\Workspace\\01_Development\\Active\\cine-stream-platform-main.zip\\public\\js\\browse.js", "source_location": "L513"}, {"id": "js_browse_renderactivepills", "label": "renderActivePills()", "file_type": "code", "source_file": "C:\\Users\\NITIN MISHRA\\Workspace\\01_Development\\Active\\cine-stream-platform-main.zip\\public\\js\\browse.js", "source_location": "L552"}, {"id": "js_browse_removefilter", "label": "removeFilter()", "file_type": "code", "source_file": "C:\\Users\\NITIN MISHRA\\Workspace\\01_Development\\Active\\cine-stream-platform-main.zip\\public\\js\\browse.js", "source_location": "L603"}, {"id": "js_browse_cssescape", "label": "cssEscape()", "file_type": "code", "source_file": "C:\\Users\\NITIN MISHRA\\Workspace\\01_Development\\Active\\cine-stream-platform-main.zip\\public\\js\\browse.js", "source_location": "L660"}, {"id": "js_browse_openmobilesidebar", "label": "openMobileSidebar()", "file_type": "code", "source_file": "C:\\Users\\NITIN MISHRA\\Workspace\\01_Development\\Active\\cine-stream-platform-main.zip\\public\\js\\browse.js", "source_location": "L672"}, {"id": "js_browse_closemobilesidebar", "label": "closeMobileSidebar()", "file_type": "code", "source_file": "C:\\Users\\NITIN MISHRA\\Workspace\\01_Development\\Active\\cine-stream-platform-main.zip\\public\\js\\browse.js", "source_location": "L682"}, {"id": "js_browse_setupsidebartoggle", "label": "setupSidebarToggle()", "file_type": "code", "source_file": "C:\\Users\\NITIN MISHRA\\Workspace\\01_Development\\Active\\cine-stream-platform-main.zip\\public\\js\\browse.js", "source_location": "L692"}, {"id": "js_browse_setupfilterevents", "label": "setupFilterEvents()", "file_type": "code", "source_file": "C:\\Users\\NITIN MISHRA\\Workspace\\01_Development\\Active\\cine-stream-platform-main.zip\\public\\js\\browse.js", "source_location": "L711"}, {"id": "js_browse_setupincategorysearch", "label": "setupInCategorySearch()", "file_type": "code", "source_file": "C:\\Users\\NITIN MISHRA\\Workspace\\01_Development\\Active\\cine-stream-platform-main.zip\\public\\js\\browse.js", "source_location": "L740"}, {"id": "js_browse_setupsubdubtoggle", "label": "setupSubDubToggle()", "file_type": "code", "source_file": "C:\\Users\\NITIN MISHRA\\Workspace\\01_Development\\Active\\cine-stream-platform-main.zip\\public\\js\\browse.js", "source_location": "L782"}, {"id": "js_browse_state", "label": "state()", "file_type": "code", "source_file": "C:\\Users\\NITIN MISHRA\\Workspace\\01_Development\\Active\\cine-stream-platform-main.zip\\public\\js\\browse.js", "source_location": "L831"}, {"id": "js_browse_setfilters", "label": "setFilters()", "file_type": "code", "source_file": "C:\\Users\\NITIN MISHRA\\Workspace\\01_Development\\Active\\cine-stream-platform-main.zip\\public\\js\\browse.js", "source_location": "L846"}], "edges": [{"source": "c_users_nitin_mishra_workspace_01_development_active_cine_stream_platform_main_zip_public_js_browse_js", "target": "js_browse_valid_categories", "relation": "contains", "confidence": "EXTRACTED", "source_file": "C:\\Users\\NITIN MISHRA\\Workspace\\01_Development\\Active\\cine-stream-platform-main.zip\\public\\js\\browse.js", "source_location": "L23", "weight": 1.0}, {"source": "c_users_nitin_mishra_workspace_01_development_active_cine_stream_platform_main_zip_public_js_browse_js", "target": "js_browse_category_meta", "relation": "contains", "confidence": "EXTRACTED", "source_file": "C:\\Users\\NITIN MISHRA\\Workspace\\01_Development\\Active\\cine-stream-platform-main.zip\\public\\js\\browse.js", "source_location": "L29", "weight": 1.0}, {"source": "c_users_nitin_mishra_workspace_01_development_active_cine_stream_platform_main_zip_public_js_browse_js", "target": "js_browse_items", "relation": "contains", "confidence": "EXTRACTED", "source_file": "C:\\Users\\NITIN MISHRA\\Workspace\\01_Development\\Active\\cine-stream-platform-main.zip\\public\\js\\browse.js", "source_location": "L69", "weight": 1.0}, {"source": "c_users_nitin_mishra_workspace_01_development_active_cine_stream_platform_main_zip_public_js_browse_js", "target": "js_browse_filters", "relation": "contains", "confidence": "EXTRACTED", "source_file": "C:\\Users\\NITIN MISHRA\\Workspace\\01_Development\\Active\\cine-stream-platform-main.zip\\public\\js\\browse.js", "source_location": "L74", "weight": 1.0}, {"source": "c_users_nitin_mishra_workspace_01_development_active_cine_stream_platform_main_zip_public_js_browse_js", "target": "js_browse_init", "relation": "contains", "confidence": "EXTRACTED", "source_file": "C:\\Users\\NITIN MISHRA\\Workspace\\01_Development\\Active\\cine-stream-platform-main.zip\\public\\js\\browse.js", "source_location": "L88", "weight": 1.0}, {"source": "c_users_nitin_mishra_workspace_01_development_active_cine_stream_platform_main_zip_public_js_browse_js", "target": "js_browse_detectcategoryfrompath", "relation": "contains", "confidence": "EXTRACTED", "source_file": "C:\\Users\\NITIN MISHRA\\Workspace\\01_Development\\Active\\cine-stream-platform-main.zip\\public\\js\\browse.js", "source_location": "L120", "weight": 1.0}, {"source": "c_users_nitin_mishra_workspace_01_development_active_cine_stream_platform_main_zip_public_js_browse_js", "target": "js_browse_renderbreadcrumb", "relation": "contains", "confidence": "EXTRACTED", "source_file": "C:\\Users\\NITIN MISHRA\\Workspace\\01_Development\\Active\\cine-stream-platform-main.zip\\public\\js\\browse.js", "source_location": "L126", "weight": 1.0}, {"source": "c_users_nitin_mishra_workspace_01_development_active_cine_stream_platform_main_zip_public_js_browse_js", "target": "js_browse_renderhero", "relation": "contains", "confidence": "EXTRACTED", "source_file": "C:\\Users\\NITIN MISHRA\\Workspace\\01_Development\\Active\\cine-stream-platform-main.zip\\public\\js\\browse.js", "source_location": "L134", "weight": 1.0}, {"source": "c_users_nitin_mishra_workspace_01_development_active_cine_stream_platform_main_zip_public_js_browse_js", "target": "js_browse_setupcategoryspecificui", "relation": "contains", "confidence": "EXTRACTED", "source_file": "C:\\Users\\NITIN MISHRA\\Workspace\\01_Development\\Active\\cine-stream-platform-main.zip\\public\\js\\browse.js", "source_location": "L153", "weight": 1.0}, {"source": "c_users_nitin_mishra_workspace_01_development_active_cine_stream_platform_main_zip_public_js_browse_js", "target": "js_browse_loadinitialpage", "relation": "contains", "confidence": "EXTRACTED", "source_file": "C:\\Users\\NITIN MISHRA\\Workspace\\01_Development\\Active\\cine-stream-platform-main.zip\\public\\js\\browse.js", "source_location": "L161", "weight": 1.0}, {"source": "c_users_nitin_mishra_workspace_01_development_active_cine_stream_platform_main_zip_public_js_browse_js", "target": "js_browse_buildquerystring", "relation": "contains", "confidence": "EXTRACTED", "source_file": "C:\\Users\\NITIN MISHRA\\Workspace\\01_Development\\Active\\cine-stream-platform-main.zip\\public\\js\\browse.js", "source_location": "L191", "weight": 1.0}, {"source": "c_users_nitin_mishra_workspace_01_development_active_cine_stream_platform_main_zip_public_js_browse_js", "target": "js_browse_fetchpage", "relation": "contains", "confidence": "EXTRACTED", "source_file": "C:\\Users\\NITIN MISHRA\\Workspace\\01_Development\\Active\\cine-stream-platform-main.zip\\public\\js\\browse.js", "source_location": "L208", "weight": 1.0}, {"source": "c_users_nitin_mishra_workspace_01_development_active_cine_stream_platform_main_zip_public_js_browse_js", "target": "js_browse_renderitems", "relation": "contains", "confidence": "EXTRACTED", "source_file": "C:\\Users\\NITIN MISHRA\\Workspace\\01_Development\\Active\\cine-stream-platform-main.zip\\public\\js\\browse.js", "source_location": "L265", "weight": 1.0}, {"source": "c_users_nitin_mishra_workspace_01_development_active_cine_stream_platform_main_zip_public_js_browse_js", "target": "js_browse_isplayableitem", "relation": "contains", "confidence": "EXTRACTED", "source_file": "C:\\Users\\NITIN MISHRA\\Workspace\\01_Development\\Active\\cine-stream-platform-main.zip\\public\\js\\browse.js", "source_location": "L313", "weight": 1.0}, {"source": "c_users_nitin_mishra_workspace_01_development_active_cine_stream_platform_main_zip_public_js_browse_js", "target": "js_browse_hasposter", "relation": "contains", "confidence": "EXTRACTED", "source_file": "C:\\Users\\NITIN MISHRA\\Workspace\\01_Development\\Active\\cine-stream-platform-main.zip\\public\\js\\browse.js", "source_location": "L324", "weight": 1.0}, {"source": "c_users_nitin_mishra_workspace_01_development_active_cine_stream_platform_main_zip_public_js_browse_js", "target": "js_browse_showloading", "relation": "contains", "confidence": "EXTRACTED", "source_file": "C:\\Users\\NITIN MISHRA\\Workspace\\01_Development\\Active\\cine-stream-platform-main.zip\\public\\js\\browse.js", "source_location": "L329", "weight": 1.0}, {"source": "c_users_nitin_mishra_workspace_01_development_active_cine_stream_platform_main_zip_public_js_browse_js", "target": "js_browse_hideloading", "relation": "contains", "confidence": "EXTRACTED", "source_file": "C:\\Users\\NITIN MISHRA\\Workspace\\01_Development\\Active\\cine-stream-platform-main.zip\\public\\js\\browse.js", "source_location": "L336", "weight": 1.0}, {"source": "c_users_nitin_mishra_workspace_01_development_active_cine_stream_platform_main_zip_public_js_browse_js", "target": "js_browse_showend", "relation": "contains", "confidence": "EXTRACTED", "source_file": "C:\\Users\\NITIN MISHRA\\Workspace\\01_Development\\Active\\cine-stream-platform-main.zip\\public\\js\\browse.js", "source_location": "L341", "weight": 1.0}, {"source": "c_users_nitin_mishra_workspace_01_development_active_cine_stream_platform_main_zip_public_js_browse_js", "target": "js_browse_setupinfinitescroll", "relation": "contains", "confidence": "EXTRACTED", "source_file": "C:\\Users\\NITIN MISHRA\\Workspace\\01_Development\\Active\\cine-stream-platform-main.zip\\public\\js\\browse.js", "source_location": "L351", "weight": 1.0}, {"source": "c_users_nitin_mishra_workspace_01_development_active_cine_stream_platform_main_zip_public_js_browse_js", "target": "js_browse_teardowninfinitescroll", "relation": "contains", "confidence": "EXTRACTED", "source_file": "C:\\Users\\NITIN MISHRA\\Workspace\\01_Development\\Active\\cine-stream-platform-main.zip\\public\\js\\browse.js", "source_location": "L376", "weight": 1.0}, {"source": "c_users_nitin_mishra_workspace_01_development_active_cine_stream_platform_main_zip_public_js_browse_js", "target": "js_browse_showretrybutton", "relation": "contains", "confidence": "EXTRACTED", "source_file": "C:\\Users\\NITIN MISHRA\\Workspace\\01_Development\\Active\\cine-stream-platform-main.zip\\public\\js\\browse.js", "source_location": "L388", "weight": 1.0}, {"source": "c_users_nitin_mishra_workspace_01_development_active_cine_stream_platform_main_zip_public_js_browse_js", "target": "js_browse_common_genres", "relation": "contains", "confidence": "EXTRACTED", "source_file": "C:\\Users\\NITIN MISHRA\\Workspace\\01_Development\\Active\\cine-stream-platform-main.zip\\public\\js\\browse.js", "source_location": "L435", "weight": 1.0}, {"source": "c_users_nitin_mishra_workspace_01_development_active_cine_stream_platform_main_zip_public_js_browse_js", "target": "js_browse_populategenrecheckboxes", "relation": "contains", "confidence": "EXTRACTED", "source_file": "C:\\Users\\NITIN MISHRA\\Workspace\\01_Development\\Active\\cine-stream-platform-main.zip\\public\\js\\browse.js", "source_location": "L446", "weight": 1.0}, {"source": "c_users_nitin_mishra_workspace_01_development_active_cine_stream_platform_main_zip_public_js_browse_js", "target": "js_browse_readfiltersfromform", "relation": "contains", "confidence": "EXTRACTED", "source_file": "C:\\Users\\NITIN MISHRA\\Workspace\\01_Development\\Active\\cine-stream-platform-main.zip\\public\\js\\browse.js", "source_location": "L458", "weight": 1.0}, {"source": "c_users_nitin_mishra_workspace_01_development_active_cine_stream_platform_main_zip_public_js_browse_js", "target": "js_browse_applyfilters", "relation": "contains", "confidence": "EXTRACTED", "source_file": "C:\\Users\\NITIN MISHRA\\Workspace\\01_Development\\Active\\cine-stream-platform-main.zip\\public\\js\\browse.js", "source_location": "L503", "weight": 1.0}, {"source": "c_users_nitin_mishra_workspace_01_development_active_cine_stream_platform_main_zip_public_js_browse_js", "target": "js_browse_clearallfilters", "relation": "contains", "confidence": "EXTRACTED", "source_file": "C:\\Users\\NITIN MISHRA\\Workspace\\01_Development\\Active\\cine-stream-platform-main.zip\\public\\js\\browse.js", "source_location": "L513", "weight": 1.0}, {"source": "c_users_nitin_mishra_workspace_01_development_active_cine_stream_platform_main_zip_public_js_browse_js", "target": "js_browse_renderactivepills", "relation": "contains", "confidence": "EXTRACTED", "source_file": "C:\\Users\\NITIN MISHRA\\Workspace\\01_Development\\Active\\cine-stream-platform-main.zip\\public\\js\\browse.js", "source_location": "L552", "weight": 1.0}, {"source": "c_users_nitin_mishra_workspace_01_development_active_cine_stream_platform_main_zip_public_js_browse_js", "target": "js_browse_removefilter", "relation": "contains", "confidence": "EXTRACTED", "source_file": "C:\\Users\\NITIN MISHRA\\Workspace\\01_Development\\Active\\cine-stream-platform-main.zip\\public\\js\\browse.js", "source_location": "L603", "weight": 1.0}, {"source": "c_users_nitin_mishra_workspace_01_development_active_cine_stream_platform_main_zip_public_js_browse_js", "target": "js_browse_cssescape", "relation": "contains", "confidence": "EXTRACTED", "source_file": "C:\\Users\\NITIN MISHRA\\Workspace\\01_Development\\Active\\cine-stream-platform-main.zip\\public\\js\\browse.js", "source_location": "L660", "weight": 1.0}, {"source": "c_users_nitin_mishra_workspace_01_development_active_cine_stream_platform_main_zip_public_js_browse_js", "target": "js_browse_openmobilesidebar", "relation": "contains", "confidence": "EXTRACTED", "source_file": "C:\\Users\\NITIN MISHRA\\Workspace\\01_Development\\Active\\cine-stream-platform-main.zip\\public\\js\\browse.js", "source_location": "L672", "weight": 1.0}, {"source": "c_users_nitin_mishra_workspace_01_development_active_cine_stream_platform_main_zip_public_js_browse_js", "target": "js_browse_closemobilesidebar", "relation": "contains", "confidence": "EXTRACTED", "source_file": "C:\\Users\\NITIN MISHRA\\Workspace\\01_Development\\Active\\cine-stream-platform-main.zip\\public\\js\\browse.js", "source_location": "L682", "weight": 1.0}, {"source": "c_users_nitin_mishra_workspace_01_development_active_cine_stream_platform_main_zip_public_js_browse_js", "target": "js_browse_setupsidebartoggle", "relation": "contains", "confidence": "EXTRACTED", "source_file": "C:\\Users\\NITIN MISHRA\\Workspace\\01_Development\\Active\\cine-stream-platform-main.zip\\public\\js\\browse.js", "source_location": "L692", "weight": 1.0}, {"source": "c_users_nitin_mishra_workspace_01_development_active_cine_stream_platform_main_zip_public_js_browse_js", "target": "js_browse_setupfilterevents", "relation": "contains", "confidence": "EXTRACTED", "source_file": "C:\\Users\\NITIN MISHRA\\Workspace\\01_Development\\Active\\cine-stream-platform-main.zip\\public\\js\\browse.js", "source_location": "L711", "weight": 1.0}, {"source": "c_users_nitin_mishra_workspace_01_development_active_cine_stream_platform_main_zip_public_js_browse_js", "target": "js_browse_setupincategorysearch", "relation": "contains", "confidence": "EXTRACTED", "source_file": "C:\\Users\\NITIN MISHRA\\Workspace\\01_Development\\Active\\cine-stream-platform-main.zip\\public\\js\\browse.js", "source_location": "L740", "weight": 1.0}, {"source": "c_users_nitin_mishra_workspace_01_development_active_cine_stream_platform_main_zip_public_js_browse_js", "target": "js_browse_setupsubdubtoggle", "relation": "contains", "confidence": "EXTRACTED", "source_file": "C:\\Users\\NITIN MISHRA\\Workspace\\01_Development\\Active\\cine-stream-platform-main.zip\\public\\js\\browse.js", "source_location": "L782", "weight": 1.0}, {"source": "c_users_nitin_mishra_workspace_01_development_active_cine_stream_platform_main_zip_public_js_browse_js", "target": "js_browse_state", "relation": "contains", "confidence": "EXTRACTED", "source_file": "C:\\Users\\NITIN MISHRA\\Workspace\\01_Development\\Active\\cine-stream-platform-main.zip\\public\\js\\browse.js", "source_location": "L831", "weight": 1.0}, {"source": "c_users_nitin_mishra_workspace_01_development_active_cine_stream_platform_main_zip_public_js_browse_js", "target": "js_browse_filters", "relation": "contains", "confidence": "EXTRACTED", "source_file": "C:\\Users\\NITIN MISHRA\\Workspace\\01_Development\\Active\\cine-stream-platform-main.zip\\public\\js\\browse.js", "source_location": "L843", "weight": 1.0}, {"source": "c_users_nitin_mishra_workspace_01_development_active_cine_stream_platform_main_zip_public_js_browse_js", "target": "js_browse_setfilters", "relation": "contains", "confidence": "EXTRACTED", "source_file": "C:\\Users\\NITIN MISHRA\\Workspace\\01_Development\\Active\\cine-stream-platform-main.zip\\public\\js\\browse.js", "source_location": "L846", "weight": 1.0}, {"source": "js_browse_init", "target": "js_browse_detectcategoryfrompath", "relation": "calls", "context": "call", "confidence": "EXTRACTED", "source_file": "C:\\Users\\NITIN MISHRA\\Workspace\\01_Development\\Active\\cine-stream-platform-main.zip\\public\\js\\browse.js", "source_location": "L89", "weight": 1.0}, {"source": "js_browse_init", "target": "js_browse_renderbreadcrumb", "relation": "calls", "context": "call", "confidence": "EXTRACTED", "source_file": "C:\\Users\\NITIN MISHRA\\Workspace\\01_Development\\Active\\cine-stream-platform-main.zip\\public\\js\\browse.js", "source_location": "L95", "weight": 1.0}, {"source": "js_browse_init", "target": "js_browse_renderhero", "relation": "calls", "context": "call", "confidence": "EXTRACTED", "source_file": "C:\\Users\\NITIN MISHRA\\Workspace\\01_Development\\Active\\cine-stream-platform-main.zip\\public\\js\\browse.js", "source_location": "L96", "weight": 1.0}, {"source": "js_browse_init", "target": "js_browse_setupcategoryspecificui", "relation": "calls", "context": "call", "confidence": "EXTRACTED", "source_file": "C:\\Users\\NITIN MISHRA\\Workspace\\01_Development\\Active\\cine-stream-platform-main.zip\\public\\js\\browse.js", "source_location": "L97", "weight": 1.0}, {"source": "js_browse_init", "target": "js_browse_populategenrecheckboxes", "relation": "calls", "context": "call", "confidence": "EXTRACTED", "source_file": "C:\\Users\\NITIN MISHRA\\Workspace\\01_Development\\Active\\cine-stream-platform-main.zip\\public\\js\\browse.js", "source_location": "L102", "weight": 1.0}, {"source": "js_browse_init", "target": "js_browse_setupsidebartoggle", "relation": "calls", "context": "call", "confidence": "EXTRACTED", "source_file": "C:\\Users\\NITIN MISHRA\\Workspace\\01_Development\\Active\\cine-stream-platform-main.zip\\public\\js\\browse.js", "source_location": "L103", "weight": 1.0}, {"source": "js_browse_init", "target": "js_browse_setupfilterevents", "relation": "calls", "context": "call", "confidence": "EXTRACTED", "source_file": "C:\\Users\\NITIN MISHRA\\Workspace\\01_Development\\Active\\cine-stream-platform-main.zip\\public\\js\\browse.js", "source_location": "L104", "weight": 1.0}, {"source": "js_browse_init", "target": "js_browse_setupincategorysearch", "relation": "calls", "context": "call", "confidence": "EXTRACTED", "source_file": "C:\\Users\\NITIN MISHRA\\Workspace\\01_Development\\Active\\cine-stream-platform-main.zip\\public\\js\\browse.js", "source_location": "L110", "weight": 1.0}, {"source": "js_browse_init", "target": "js_browse_setupsubdubtoggle", "relation": "calls", "context": "call", "confidence": "EXTRACTED", "source_file": "C:\\Users\\NITIN MISHRA\\Workspace\\01_Development\\Active\\cine-stream-platform-main.zip\\public\\js\\browse.js", "source_location": "L111", "weight": 1.0}, {"source": "js_browse_init", "target": "js_browse_loadinitialpage", "relation": "calls", "context": "call", "confidence": "EXTRACTED", "source_file": "C:\\Users\\NITIN MISHRA\\Workspace\\01_Development\\Active\\cine-stream-platform-main.zip\\public\\js\\browse.js", "source_location": "L114", "weight": 1.0}, {"source": "js_browse_loadinitialpage", "target": "js_browse_teardowninfinitescroll", "relation": "calls", "context": "call", "confidence": "EXTRACTED", "source_file": "C:\\Users\\NITIN MISHRA\\Workspace\\01_Development\\Active\\cine-stream-platform-main.zip\\public\\js\\browse.js", "source_location": "L179", "weight": 1.0}, {"source": "js_browse_loadinitialpage", "target": "js_browse_fetchpage", "relation": "calls", "context": "call", "confidence": "EXTRACTED", "source_file": "C:\\Users\\NITIN MISHRA\\Workspace\\01_Development\\Active\\cine-stream-platform-main.zip\\public\\js\\browse.js", "source_location": "L181", "weight": 1.0}, {"source": "js_browse_loadinitialpage", "target": "js_browse_setupinfinitescroll", "relation": "calls", "context": "call", "confidence": "EXTRACTED", "source_file": "C:\\Users\\NITIN MISHRA\\Workspace\\01_Development\\Active\\cine-stream-platform-main.zip\\public\\js\\browse.js", "source_location": "L185", "weight": 1.0}, {"source": "js_browse_fetchpage", "target": "js_browse_showloading", "relation": "calls", "context": "call", "confidence": "EXTRACTED", "source_file": "C:\\Users\\NITIN MISHRA\\Workspace\\01_Development\\Active\\cine-stream-platform-main.zip\\public\\js\\browse.js", "source_location": "L217", "weight": 1.0}, {"source": "js_browse_fetchpage", "target": "js_browse_buildquerystring", "relation": "calls", "context": "call", "confidence": "EXTRACTED", "source_file": "C:\\Users\\NITIN MISHRA\\Workspace\\01_Development\\Active\\cine-stream-platform-main.zip\\public\\js\\browse.js", "source_location": "L220", "weight": 1.0}, {"source": "js_browse_fetchpage", "target": "js_browse_renderitems", "relation": "calls", "context": "call", "confidence": "EXTRACTED", "source_file": "C:\\Users\\NITIN MISHRA\\Workspace\\01_Development\\Active\\cine-stream-platform-main.zip\\public\\js\\browse.js", "source_location": "L230", "weight": 1.0}, {"source": "js_browse_fetchpage", "target": "js_browse_renderactivepills", "relation": "calls", "context": "call", "confidence": "EXTRACTED", "source_file": "C:\\Users\\NITIN MISHRA\\Workspace\\01_Development\\Active\\cine-stream-platform-main.zip\\public\\js\\browse.js", "source_location": "L236", "weight": 1.0}, {"source": "js_browse_fetchpage", "target": "js_browse_showend", "relation": "calls", "context": "call", "confidence": "EXTRACTED", "source_file": "C:\\Users\\NITIN MISHRA\\Workspace\\01_Development\\Active\\cine-stream-platform-main.zip\\public\\js\\browse.js", "source_location": "L241", "weight": 1.0}, {"source": "js_browse_fetchpage", "target": "js_browse_teardowninfinitescroll", "relation": "calls", "context": "call", "confidence": "EXTRACTED", "source_file": "C:\\Users\\NITIN MISHRA\\Workspace\\01_Development\\Active\\cine-stream-platform-main.zip\\public\\js\\browse.js", "source_location": "L242", "weight": 1.0}, {"source": "js_browse_fetchpage", "target": "js_browse_showretrybutton", "relation": "calls", "context": "call", "confidence": "EXTRACTED", "source_file": "C:\\Users\\NITIN MISHRA\\Workspace\\01_Development\\Active\\cine-stream-platform-main.zip\\public\\js\\browse.js", "source_location": "L256", "weight": 1.0}, {"source": "js_browse_fetchpage", "target": "js_browse_hideloading", "relation": "calls", "context": "call", "confidence": "EXTRACTED", "source_file": "C:\\Users\\NITIN MISHRA\\Workspace\\01_Development\\Active\\cine-stream-platform-main.zip\\public\\js\\browse.js", "source_location": "L260", "weight": 1.0}, {"source": "js_browse_applyfilters", "target": "js_browse_readfiltersfromform", "relation": "calls", "context": "call", "confidence": "EXTRACTED", "source_file": "C:\\Users\\NITIN MISHRA\\Workspace\\01_Development\\Active\\cine-stream-platform-main.zip\\public\\js\\browse.js", "source_location": "L504", "weight": 1.0}, {"source": "js_browse_applyfilters", "target": "js_browse_renderactivepills", "relation": "calls", "context": "call", "confidence": "EXTRACTED", "source_file": "C:\\Users\\NITIN MISHRA\\Workspace\\01_Development\\Active\\cine-stream-platform-main.zip\\public\\js\\browse.js", "source_location": "L505", "weight": 1.0}, {"source": "js_browse_applyfilters", "target": "js_browse_loadinitialpage", "relation": "calls", "context": "call", "confidence": "EXTRACTED", "source_file": "C:\\Users\\NITIN MISHRA\\Workspace\\01_Development\\Active\\cine-stream-platform-main.zip\\public\\js\\browse.js", "source_location": "L506", "weight": 1.0}, {"source": "js_browse_applyfilters", "target": "js_browse_closemobilesidebar", "relation": "calls", "context": "call", "confidence": "EXTRACTED", "source_file": "C:\\Users\\NITIN MISHRA\\Workspace\\01_Development\\Active\\cine-stream-platform-main.zip\\public\\js\\browse.js", "source_location": "L507", "weight": 1.0}, {"source": "js_browse_clearallfilters", "target": "js_browse_renderactivepills", "relation": "calls", "context": "call", "confidence": "EXTRACTED", "source_file": "C:\\Users\\NITIN MISHRA\\Workspace\\01_Development\\Active\\cine-stream-platform-main.zip\\public\\js\\browse.js", "source_location": "L544", "weight": 1.0}, {"source": "js_browse_clearallfilters", "target": "js_browse_loadinitialpage", "relation": "calls", "context": "call", "confidence": "EXTRACTED", "source_file": "C:\\Users\\NITIN MISHRA\\Workspace\\01_Development\\Active\\cine-stream-platform-main.zip\\public\\js\\browse.js", "source_location": "L545", "weight": 1.0}, {"source": "js_browse_removefilter", "target": "js_browse_cssescape", "relation": "calls", "context": "call", "confidence": "EXTRACTED", "source_file": "C:\\Users\\NITIN MISHRA\\Workspace\\01_Development\\Active\\cine-stream-platform-main.zip\\public\\js\\browse.js", "source_location": "L607", "weight": 1.0}, {"source": "js_browse_removefilter", "target": "js_browse_renderactivepills", "relation": "calls", "context": "call", "confidence": "EXTRACTED", "source_file": "C:\\Users\\NITIN MISHRA\\Workspace\\01_Development\\Active\\cine-stream-platform-main.zip\\public\\js\\browse.js", "source_location": "L653", "weight": 1.0}, {"source": "js_browse_removefilter", "target": "js_browse_loadinitialpage", "relation": "calls", "context": "call", "confidence": "EXTRACTED", "source_file": "C:\\Users\\NITIN MISHRA\\Workspace\\01_Development\\Active\\cine-stream-platform-main.zip\\public\\js\\browse.js", "source_location": "L654", "weight": 1.0}, {"source": "js_browse_setupsidebartoggle", "target": "js_browse_openmobilesidebar", "relation": "calls", "context": "call", "confidence": "EXTRACTED", "source_file": "C:\\Users\\NITIN MISHRA\\Workspace\\01_Development\\Active\\cine-stream-platform-main.zip\\public\\js\\browse.js", "source_location": "L706", "weight": 1.0}], "raw_calls": [{"caller_nid": "js_browse_init", "callee": "includes", "is_member_call": true, "source_file": "C:\\Users\\NITIN MISHRA\\Workspace\\01_Development\\Active\\cine-stream-platform-main.zip\\public\\js\\browse.js", "source_location": "L90"}, {"caller_nid": "js_browse_detectcategoryfrompath", "callee": "match", "is_member_call": true, "source_file": "C:\\Users\\NITIN MISHRA\\Workspace\\01_Development\\Active\\cine-stream-platform-main.zip\\public\\js\\browse.js", "source_location": "L122"}, {"caller_nid": "js_browse_detectcategoryfrompath", "callee": "toLowerCase", "is_member_call": true, "source_file": "C:\\Users\\NITIN MISHRA\\Workspace\\01_Development\\Active\\cine-stream-platform-main.zip\\public\\js\\browse.js", "source_location": "L123"}, {"caller_nid": "js_browse_renderbreadcrumb", "callee": "getElementById", "is_member_call": true, "source_file": "C:\\Users\\NITIN MISHRA\\Workspace\\01_Development\\Active\\cine-stream-platform-main.zip\\public\\js\\browse.js", "source_location": "L128"}, {"caller_nid": "js_browse_renderhero", "callee": "getElementById", "is_member_call": true, "source_file": "C:\\Users\\NITIN MISHRA\\Workspace\\01_Development\\Active\\cine-stream-platform-main.zip\\public\\js\\browse.js", "source_location": "L136"}, {"caller_nid": "js_browse_renderhero", "callee": "getElementById", "is_member_call": true, "source_file": "C:\\Users\\NITIN MISHRA\\Workspace\\01_Development\\Active\\cine-stream-platform-main.zip\\public\\js\\browse.js", "source_location": "L137"}, {"caller_nid": "js_browse_renderhero", "callee": "getElementById", "is_member_call": true, "source_file": "C:\\Users\\NITIN MISHRA\\Workspace\\01_Development\\Active\\cine-stream-platform-main.zip\\public\\js\\browse.js", "source_location": "L138"}, {"caller_nid": "js_browse_renderhero", "callee": "getElementById", "is_member_call": true, "source_file": "C:\\Users\\NITIN MISHRA\\Workspace\\01_Development\\Active\\cine-stream-platform-main.zip\\public\\js\\browse.js", "source_location": "L147"}, {"caller_nid": "js_browse_setupcategoryspecificui", "callee": "getElementById", "is_member_call": true, "source_file": "C:\\Users\\NITIN MISHRA\\Workspace\\01_Development\\Active\\cine-stream-platform-main.zip\\public\\js\\browse.js", "source_location": "L154"}, {"caller_nid": "js_browse_loadinitialpage", "callee": "getElementById", "is_member_call": true, "source_file": "C:\\Users\\NITIN MISHRA\\Workspace\\01_Development\\Active\\cine-stream-platform-main.zip\\public\\js\\browse.js", "source_location": "L166"}, {"caller_nid": "js_browse_loadinitialpage", "callee": "getElementById", "is_member_call": true, "source_file": "C:\\Users\\NITIN MISHRA\\Workspace\\01_Development\\Active\\cine-stream-platform-main.zip\\public\\js\\browse.js", "source_location": "L171"}, {"caller_nid": "js_browse_loadinitialpage", "callee": "getElementById", "is_member_call": true, "source_file": "C:\\Users\\NITIN MISHRA\\Workspace\\01_Development\\Active\\cine-stream-platform-main.zip\\public\\js\\browse.js", "source_location": "L173"}, {"caller_nid": "js_browse_loadinitialpage", "callee": "remove", "is_member_call": true, "source_file": "C:\\Users\\NITIN MISHRA\\Workspace\\01_Development\\Active\\cine-stream-platform-main.zip\\public\\js\\browse.js", "source_location": "L174"}, {"caller_nid": "js_browse_buildquerystring", "callee": "set", "is_member_call": true, "source_file": "C:\\Users\\NITIN MISHRA\\Workspace\\01_Development\\Active\\cine-stream-platform-main.zip\\public\\js\\browse.js", "source_location": "L193"}, {"caller_nid": "js_browse_buildquerystring", "callee": "String", "is_member_call": false, "source_file": "C:\\Users\\NITIN MISHRA\\Workspace\\01_Development\\Active\\cine-stream-platform-main.zip\\public\\js\\browse.js", "source_location": "L193"}, {"caller_nid": "js_browse_buildquerystring", "callee": "set", "is_member_call": true, "source_file": "C:\\Users\\NITIN MISHRA\\Workspace\\01_Development\\Active\\cine-stream-platform-main.zip\\public\\js\\browse.js", "source_location": "L194"}, {"caller_nid": "js_browse_buildquerystring", "callee": "String", "is_member_call": false, "source_file": "C:\\Users\\NITIN MISHRA\\Workspace\\01_Development\\Active\\cine-stream-platform-main.zip\\public\\js\\browse.js", "source_location": "L194"}, {"caller_nid": "js_browse_buildquerystring", "callee": "set", "is_member_call": true, "source_file": "C:\\Users\\NITIN MISHRA\\Workspace\\01_Development\\Active\\cine-stream-platform-main.zip\\public\\js\\browse.js", "source_location": "L195"}, {"caller_nid": "js_browse_buildquerystring", "callee": "join", "is_member_call": true, "source_file": "C:\\Users\\NITIN MISHRA\\Workspace\\01_Development\\Active\\cine-stream-platform-main.zip\\public\\js\\browse.js", "source_location": "L195"}, {"caller_nid": "js_browse_buildquerystring", "callee": "set", "is_member_call": true, "source_file": "C:\\Users\\NITIN MISHRA\\Workspace\\01_Development\\Active\\cine-stream-platform-main.zip\\public\\js\\browse.js", "source_location": "L196"}, {"caller_nid": "js_browse_buildquerystring", "callee": "String", "is_member_call": false, "source_file": "C:\\Users\\NITIN MISHRA\\Workspace\\01_Development\\Active\\cine-stream-platform-main.zip\\public\\js\\browse.js", "source_location": "L196"}, {"caller_nid": "js_browse_buildquerystring", "callee": "set", "is_member_call": true, "source_file": "C:\\Users\\NITIN MISHRA\\Workspace\\01_Development\\Active\\cine-stream-platform-main.zip\\public\\js\\browse.js", "source_location": "L197"}, {"caller_nid": "js_browse_buildquerystring", "callee": "String", "is_member_call": false, "source_file": "C:\\Users\\NITIN MISHRA\\Workspace\\01_Development\\Active\\cine-stream-platform-main.zip\\public\\js\\browse.js", "source_location": "L197"}, {"caller_nid": "js_browse_buildquerystring", "callee": "set", "is_member_call": true, "source_file": "C:\\Users\\NITIN MISHRA\\Workspace\\01_Development\\Active\\cine-stream-platform-main.zip\\public\\js\\browse.js", "source_location": "L198"}, {"caller_nid": "js_browse_buildquerystring", "callee": "String", "is_member_call": false, "source_file": "C:\\Users\\NITIN MISHRA\\Workspace\\01_Development\\Active\\cine-stream-platform-main.zip\\public\\js\\browse.js", "source_location": "L198"}, {"caller_nid": "js_browse_buildquerystring", "callee": "set", "is_member_call": true, "source_file": "C:\\Users\\NITIN MISHRA\\Workspace\\01_Development\\Active\\cine-stream-platform-main.zip\\public\\js\\browse.js", "source_location": "L199"}, {"caller_nid": "js_browse_buildquerystring", "callee": "String", "is_member_call": false, "source_file": "C:\\Users\\NITIN MISHRA\\Workspace\\01_Development\\Active\\cine-stream-platform-main.zip\\public\\js\\browse.js", "source_location": "L199"}, {"caller_nid": "js_browse_buildquerystring", "callee": "set", "is_member_call": true, "source_file": "C:\\Users\\NITIN MISHRA\\Workspace\\01_Development\\Active\\cine-stream-platform-main.zip\\public\\js\\browse.js", "source_location": "L200"}, {"caller_nid": "js_browse_buildquerystring", "callee": "join", "is_member_call": true, "source_file": "C:\\Users\\NITIN MISHRA\\Workspace\\01_Development\\Active\\cine-stream-platform-main.zip\\public\\js\\browse.js", "source_location": "L200"}, {"caller_nid": "js_browse_buildquerystring", "callee": "set", "is_member_call": true, "source_file": "C:\\Users\\NITIN MISHRA\\Workspace\\01_Development\\Active\\cine-stream-platform-main.zip\\public\\js\\browse.js", "source_location": "L201"}, {"caller_nid": "js_browse_buildquerystring", "callee": "join", "is_member_call": true, "source_file": "C:\\Users\\NITIN MISHRA\\Workspace\\01_Development\\Active\\cine-stream-platform-main.zip\\public\\js\\browse.js", "source_location": "L201"}, {"caller_nid": "js_browse_buildquerystring", "callee": "set", "is_member_call": true, "source_file": "C:\\Users\\NITIN MISHRA\\Workspace\\01_Development\\Active\\cine-stream-platform-main.zip\\public\\js\\browse.js", "source_location": "L202"}, {"caller_nid": "js_browse_buildquerystring", "callee": "set", "is_member_call": true, "source_file": "C:\\Users\\NITIN MISHRA\\Workspace\\01_Development\\Active\\cine-stream-platform-main.zip\\public\\js\\browse.js", "source_location": "L203"}, {"caller_nid": "js_browse_buildquerystring", "callee": "set", "is_member_call": true, "source_file": "C:\\Users\\NITIN MISHRA\\Workspace\\01_Development\\Active\\cine-stream-platform-main.zip\\public\\js\\browse.js", "source_location": "L204"}, {"caller_nid": "js_browse_buildquerystring", "callee": "toString", "is_member_call": true, "source_file": "C:\\Users\\NITIN MISHRA\\Workspace\\01_Development\\Active\\cine-stream-platform-main.zip\\public\\js\\browse.js", "source_location": "L205"}, {"caller_nid": "js_browse_fetchpage", "callee": "getElementById", "is_member_call": true, "source_file": "C:\\Users\\NITIN MISHRA\\Workspace\\01_Development\\Active\\cine-stream-platform-main.zip\\public\\js\\browse.js", "source_location": "L214"}, {"caller_nid": "js_browse_fetchpage", "callee": "remove", "is_member_call": true, "source_file": "C:\\Users\\NITIN MISHRA\\Workspace\\01_Development\\Active\\cine-stream-platform-main.zip\\public\\js\\browse.js", "source_location": "L215"}, {"caller_nid": "js_browse_fetchpage", "callee": "apiRequest", "is_member_call": false, "source_file": "C:\\Users\\NITIN MISHRA\\Workspace\\01_Development\\Active\\cine-stream-platform-main.zip\\public\\js\\browse.js", "source_location": "L224"}, {"caller_nid": "js_browse_fetchpage", "callee": "isArray", "is_member_call": true, "source_file": "C:\\Users\\NITIN MISHRA\\Workspace\\01_Development\\Active\\cine-stream-platform-main.zip\\public\\js\\browse.js", "source_location": "L226"}, {"caller_nid": "js_browse_fetchpage", "callee": "concat", "is_member_call": true, "source_file": "C:\\Users\\NITIN MISHRA\\Workspace\\01_Development\\Active\\cine-stream-platform-main.zip\\public\\js\\browse.js", "source_location": "L228"}, {"caller_nid": "js_browse_fetchpage", "callee": "error", "is_member_call": true, "source_file": "C:\\Users\\NITIN MISHRA\\Workspace\\01_Development\\Active\\cine-stream-platform-main.zip\\public\\js\\browse.js", "source_location": "L248"}, {"caller_nid": "js_browse_fetchpage", "callee": "getElementById", "is_member_call": true, "source_file": "C:\\Users\\NITIN MISHRA\\Workspace\\01_Development\\Active\\cine-stream-platform-main.zip\\public\\js\\browse.js", "source_location": "L249"}, {"caller_nid": "js_browse_renderitems", "callee": "getElementById", "is_member_call": true, "source_file": "C:\\Users\\NITIN MISHRA\\Workspace\\01_Development\\Active\\cine-stream-platform-main.zip\\public\\js\\browse.js", "source_location": "L266"}, {"caller_nid": "js_browse_renderitems", "callee": "filter", "is_member_call": true, "source_file": "C:\\Users\\NITIN MISHRA\\Workspace\\01_Development\\Active\\cine-stream-platform-main.zip\\public\\js\\browse.js", "source_location": "L273"}, {"caller_nid": "js_browse_renderitems", "callee": "escapeHtml", "is_member_call": false, "source_file": "C:\\Users\\NITIN MISHRA\\Workspace\\01_Development\\Active\\cine-stream-platform-main.zip\\public\\js\\browse.js", "source_location": "L282"}, {"caller_nid": "js_browse_renderitems", "callee": "escapeHtml", "is_member_call": false, "source_file": "C:\\Users\\NITIN MISHRA\\Workspace\\01_Development\\Active\\cine-stream-platform-main.zip\\public\\js\\browse.js", "source_location": "L283"}, {"caller_nid": "js_browse_renderitems", "callee": "join", "is_member_call": true, "source_file": "C:\\Users\\NITIN MISHRA\\Workspace\\01_Development\\Active\\cine-stream-platform-main.zip\\public\\js\\browse.js", "source_location": "L289"}, {"caller_nid": "js_browse_renderitems", "callee": "map", "is_member_call": true, "source_file": "C:\\Users\\NITIN MISHRA\\Workspace\\01_Development\\Active\\cine-stream-platform-main.zip\\public\\js\\browse.js", "source_location": "L289"}, {"caller_nid": "js_browse_renderitems", "callee": "insertAdjacentHTML", "is_member_call": true, "source_file": "C:\\Users\\NITIN MISHRA\\Workspace\\01_Development\\Active\\cine-stream-platform-main.zip\\public\\js\\browse.js", "source_location": "L291"}, {"caller_nid": "js_browse_renderitems", "callee": "addEventListener", "is_member_call": true, "source_file": "C:\\Users\\NITIN MISHRA\\Workspace\\01_Development\\Active\\cine-stream-platform-main.zip\\public\\js\\browse.js", "source_location": "L302"}, {"caller_nid": "js_browse_isplayableitem", "callee": "trim", "is_member_call": true, "source_file": "C:\\Users\\NITIN MISHRA\\Workspace\\01_Development\\Active\\cine-stream-platform-main.zip\\public\\js\\browse.js", "source_location": "L320"}, {"caller_nid": "js_browse_isplayableitem", "callee": "String", "is_member_call": false, "source_file": "C:\\Users\\NITIN MISHRA\\Workspace\\01_Development\\Active\\cine-stream-platform-main.zip\\public\\js\\browse.js", "source_location": "L320"}, {"caller_nid": "js_browse_hasposter", "callee": "trim", "is_member_call": true, "source_file": "C:\\Users\\NITIN MISHRA\\Workspace\\01_Development\\Active\\cine-stream-platform-main.zip\\public\\js\\browse.js", "source_location": "L325"}, {"caller_nid": "js_browse_hasposter", "callee": "String", "is_member_call": false, "source_file": "C:\\Users\\NITIN MISHRA\\Workspace\\01_Development\\Active\\cine-stream-platform-main.zip\\public\\js\\browse.js", "source_location": "L325"}, {"caller_nid": "js_browse_hasposter", "callee": "test", "is_member_call": true, "source_file": "C:\\Users\\NITIN MISHRA\\Workspace\\01_Development\\Active\\cine-stream-platform-main.zip\\public\\js\\browse.js", "source_location": "L326"}, {"caller_nid": "js_browse_showloading", "callee": "getElementById", "is_member_call": true, "source_file": "C:\\Users\\NITIN MISHRA\\Workspace\\01_Development\\Active\\cine-stream-platform-main.zip\\public\\js\\browse.js", "source_location": "L330"}, {"caller_nid": "js_browse_showloading", "callee": "getElementById", "is_member_call": true, "source_file": "C:\\Users\\NITIN MISHRA\\Workspace\\01_Development\\Active\\cine-stream-platform-main.zip\\public\\js\\browse.js", "source_location": "L332"}, {"caller_nid": "js_browse_hideloading", "callee": "getElementById", "is_member_call": true, "source_file": "C:\\Users\\NITIN MISHRA\\Workspace\\01_Development\\Active\\cine-stream-platform-main.zip\\public\\js\\browse.js", "source_location": "L337"}, {"caller_nid": "js_browse_showend", "callee": "getElementById", "is_member_call": true, "source_file": "C:\\Users\\NITIN MISHRA\\Workspace\\01_Development\\Active\\cine-stream-platform-main.zip\\public\\js\\browse.js", "source_location": "L342"}, {"caller_nid": "js_browse_setupinfinitescroll", "callee": "getElementById", "is_member_call": true, "source_file": "C:\\Users\\NITIN MISHRA\\Workspace\\01_Development\\Active\\cine-stream-platform-main.zip\\public\\js\\browse.js", "source_location": "L352"}, {"caller_nid": "js_browse_setupinfinitescroll", "callee": "observe", "is_member_call": true, "source_file": "C:\\Users\\NITIN MISHRA\\Workspace\\01_Development\\Active\\cine-stream-platform-main.zip\\public\\js\\browse.js", "source_location": "L373"}, {"caller_nid": "js_browse_teardowninfinitescroll", "callee": "disconnect", "is_member_call": true, "source_file": "C:\\Users\\NITIN MISHRA\\Workspace\\01_Development\\Active\\cine-stream-platform-main.zip\\public\\js\\browse.js", "source_location": "L378"}, {"caller_nid": "js_browse_showretrybutton", "callee": "getElementById", "is_member_call": true, "source_file": "C:\\Users\\NITIN MISHRA\\Workspace\\01_Development\\Active\\cine-stream-platform-main.zip\\public\\js\\browse.js", "source_location": "L389"}, {"caller_nid": "js_browse_showretrybutton", "callee": "getElementById", "is_member_call": true, "source_file": "C:\\Users\\NITIN MISHRA\\Workspace\\01_Development\\Active\\cine-stream-platform-main.zip\\public\\js\\browse.js", "source_location": "L390"}, {"caller_nid": "js_browse_showretrybutton", "callee": "getElementById", "is_member_call": true, "source_file": "C:\\Users\\NITIN MISHRA\\Workspace\\01_Development\\Active\\cine-stream-platform-main.zip\\public\\js\\browse.js", "source_location": "L394"}, {"caller_nid": "js_browse_showretrybutton", "callee": "remove", "is_member_call": true, "source_file": "C:\\Users\\NITIN MISHRA\\Workspace\\01_Development\\Active\\cine-stream-platform-main.zip\\public\\js\\browse.js", "source_location": "L395"}, {"caller_nid": "js_browse_showretrybutton", "callee": "createElement", "is_member_call": true, "source_file": "C:\\Users\\NITIN MISHRA\\Workspace\\01_Development\\Active\\cine-stream-platform-main.zip\\public\\js\\browse.js", "source_location": "L397"}, {"caller_nid": "js_browse_showretrybutton", "callee": "join", "is_member_call": true, "source_file": "C:\\Users\\NITIN MISHRA\\Workspace\\01_Development\\Active\\cine-stream-platform-main.zip\\public\\js\\browse.js", "source_location": "L401"}, {"caller_nid": "js_browse_showretrybutton", "callee": "addEventListener", "is_member_call": true, "source_file": "C:\\Users\\NITIN MISHRA\\Workspace\\01_Development\\Active\\cine-stream-platform-main.zip\\public\\js\\browse.js", "source_location": "L414"}, {"caller_nid": "js_browse_showretrybutton", "callee": "insertBefore", "is_member_call": true, "source_file": "C:\\Users\\NITIN MISHRA\\Workspace\\01_Development\\Active\\cine-stream-platform-main.zip\\public\\js\\browse.js", "source_location": "L421"}, {"caller_nid": "js_browse_populategenrecheckboxes", "callee": "getElementById", "is_member_call": true, "source_file": "C:\\Users\\NITIN MISHRA\\Workspace\\01_Development\\Active\\cine-stream-platform-main.zip\\public\\js\\browse.js", "source_location": "L447"}, {"caller_nid": "js_browse_populategenrecheckboxes", "callee": "join", "is_member_call": true, "source_file": "C:\\Users\\NITIN MISHRA\\Workspace\\01_Development\\Active\\cine-stream-platform-main.zip\\public\\js\\browse.js", "source_location": "L449"}, {"caller_nid": "js_browse_populategenrecheckboxes", "callee": "map", "is_member_call": true, "source_file": "C:\\Users\\NITIN MISHRA\\Workspace\\01_Development\\Active\\cine-stream-platform-main.zip\\public\\js\\browse.js", "source_location": "L449"}, {"caller_nid": "js_browse_readfiltersfromform", "callee": "forEach", "is_member_call": true, "source_file": "C:\\Users\\NITIN MISHRA\\Workspace\\01_Development\\Active\\cine-stream-platform-main.zip\\public\\js\\browse.js", "source_location": "L472"}, {"caller_nid": "js_browse_readfiltersfromform", "callee": "querySelectorAll", "is_member_call": true, "source_file": "C:\\Users\\NITIN MISHRA\\Workspace\\01_Development\\Active\\cine-stream-platform-main.zip\\public\\js\\browse.js", "source_location": "L472"}, {"caller_nid": "js_browse_readfiltersfromform", "callee": "getElementById", "is_member_call": true, "source_file": "C:\\Users\\NITIN MISHRA\\Workspace\\01_Development\\Active\\cine-stream-platform-main.zip\\public\\js\\browse.js", "source_location": "L476"}, {"caller_nid": "js_browse_readfiltersfromform", "callee": "getElementById", "is_member_call": true, "source_file": "C:\\Users\\NITIN MISHRA\\Workspace\\01_Development\\Active\\cine-stream-platform-main.zip\\public\\js\\browse.js", "source_location": "L477"}, {"caller_nid": "js_browse_readfiltersfromform", "callee": "parseInt", "is_member_call": false, "source_file": "C:\\Users\\NITIN MISHRA\\Workspace\\01_Development\\Active\\cine-stream-platform-main.zip\\public\\js\\browse.js", "source_location": "L478"}, {"caller_nid": "js_browse_readfiltersfromform", "callee": "parseInt", "is_member_call": false, "source_file": "C:\\Users\\NITIN MISHRA\\Workspace\\01_Development\\Active\\cine-stream-platform-main.zip\\public\\js\\browse.js", "source_location": "L479"}, {"caller_nid": "js_browse_readfiltersfromform", "callee": "getElementById", "is_member_call": true, "source_file": "C:\\Users\\NITIN MISHRA\\Workspace\\01_Development\\Active\\cine-stream-platform-main.zip\\public\\js\\browse.js", "source_location": "L481"}, {"caller_nid": "js_browse_readfiltersfromform", "callee": "getElementById", "is_member_call": true, "source_file": "C:\\Users\\NITIN MISHRA\\Workspace\\01_Development\\Active\\cine-stream-platform-main.zip\\public\\js\\browse.js", "source_location": "L482"}, {"caller_nid": "js_browse_readfiltersfromform", "callee": "parseFloat", "is_member_call": false, "source_file": "C:\\Users\\NITIN MISHRA\\Workspace\\01_Development\\Active\\cine-stream-platform-main.zip\\public\\js\\browse.js", "source_location": "L483"}, {"caller_nid": "js_browse_readfiltersfromform", "callee": "parseFloat", "is_member_call": false, "source_file": "C:\\Users\\NITIN MISHRA\\Workspace\\01_Development\\Active\\cine-stream-platform-main.zip\\public\\js\\browse.js", "source_location": "L484"}, {"caller_nid": "js_browse_readfiltersfromform", "callee": "forEach", "is_member_call": true, "source_file": "C:\\Users\\NITIN MISHRA\\Workspace\\01_Development\\Active\\cine-stream-platform-main.zip\\public\\js\\browse.js", "source_location": "L486"}, {"caller_nid": "js_browse_readfiltersfromform", "callee": "querySelectorAll", "is_member_call": true, "source_file": "C:\\Users\\NITIN MISHRA\\Workspace\\01_Development\\Active\\cine-stream-platform-main.zip\\public\\js\\browse.js", "source_location": "L486"}, {"caller_nid": "js_browse_readfiltersfromform", "callee": "forEach", "is_member_call": true, "source_file": "C:\\Users\\NITIN MISHRA\\Workspace\\01_Development\\Active\\cine-stream-platform-main.zip\\public\\js\\browse.js", "source_location": "L490"}, {"caller_nid": "js_browse_readfiltersfromform", "callee": "querySelectorAll", "is_member_call": true, "source_file": "C:\\Users\\NITIN MISHRA\\Workspace\\01_Development\\Active\\cine-stream-platform-main.zip\\public\\js\\browse.js", "source_location": "L490"}, {"caller_nid": "js_browse_readfiltersfromform", "callee": "getElementById", "is_member_call": true, "source_file": "C:\\Users\\NITIN MISHRA\\Workspace\\01_Development\\Active\\cine-stream-platform-main.zip\\public\\js\\browse.js", "source_location": "L494"}, {"caller_nid": "js_browse_readfiltersfromform", "callee": "assign", "is_member_call": true, "source_file": "C:\\Users\\NITIN MISHRA\\Workspace\\01_Development\\Active\\cine-stream-platform-main.zip\\public\\js\\browse.js", "source_location": "L497"}, {"caller_nid": "js_browse_clearallfilters", "callee": "forEach", "is_member_call": true, "source_file": "C:\\Users\\NITIN MISHRA\\Workspace\\01_Development\\Active\\cine-stream-platform-main.zip\\public\\js\\browse.js", "source_location": "L514"}, {"caller_nid": "js_browse_clearallfilters", "callee": "querySelectorAll", "is_member_call": true, "source_file": "C:\\Users\\NITIN MISHRA\\Workspace\\01_Development\\Active\\cine-stream-platform-main.zip\\public\\js\\browse.js", "source_location": "L514"}, {"caller_nid": "js_browse_clearallfilters", "callee": "forEach", "is_member_call": true, "source_file": "C:\\Users\\NITIN MISHRA\\Workspace\\01_Development\\Active\\cine-stream-platform-main.zip\\public\\js\\browse.js", "source_location": "L517"}, {"caller_nid": "js_browse_clearallfilters", "callee": "querySelectorAll", "is_member_call": true, "source_file": "C:\\Users\\NITIN MISHRA\\Workspace\\01_Development\\Active\\cine-stream-platform-main.zip\\public\\js\\browse.js", "source_location": "L517"}, {"caller_nid": "js_browse_clearallfilters", "callee": "forEach", "is_member_call": true, "source_file": "C:\\Users\\NITIN MISHRA\\Workspace\\01_Development\\Active\\cine-stream-platform-main.zip\\public\\js\\browse.js", "source_location": "L520"}, {"caller_nid": "js_browse_clearallfilters", "callee": "querySelectorAll", "is_member_call": true, "source_file": "C:\\Users\\NITIN MISHRA\\Workspace\\01_Development\\Active\\cine-stream-platform-main.zip\\public\\js\\browse.js", "source_location": "L520"}, {"caller_nid": "js_browse_clearallfilters", "callee": "getElementById", "is_member_call": true, "source_file": "C:\\Users\\NITIN MISHRA\\Workspace\\01_Development\\Active\\cine-stream-platform-main.zip\\public\\js\\browse.js", "source_location": "L524"}, {"caller_nid": "js_browse_clearallfilters", "callee": "getElementById", "is_member_call": true, "source_file": "C:\\Users\\NITIN MISHRA\\Workspace\\01_Development\\Active\\cine-stream-platform-main.zip\\public\\js\\browse.js", "source_location": "L525"}, {"caller_nid": "js_browse_clearallfilters", "callee": "getElementById", "is_member_call": true, "source_file": "C:\\Users\\NITIN MISHRA\\Workspace\\01_Development\\Active\\cine-stream-platform-main.zip\\public\\js\\browse.js", "source_location": "L526"}, {"caller_nid": "js_browse_clearallfilters", "callee": "getElementById", "is_member_call": true, "source_file": "C:\\Users\\NITIN MISHRA\\Workspace\\01_Development\\Active\\cine-stream-platform-main.zip\\public\\js\\browse.js", "source_location": "L527"}, {"caller_nid": "js_browse_clearallfilters", "callee": "getElementById", "is_member_call": true, "source_file": "C:\\Users\\NITIN MISHRA\\Workspace\\01_Development\\Active\\cine-stream-platform-main.zip\\public\\js\\browse.js", "source_location": "L528"}, {"caller_nid": "js_browse_renderactivepills", "callee": "getElementById", "is_member_call": true, "source_file": "C:\\Users\\NITIN MISHRA\\Workspace\\01_Development\\Active\\cine-stream-platform-main.zip\\public\\js\\browse.js", "source_location": "L553"}, {"caller_nid": "js_browse_renderactivepills", "callee": "forEach", "is_member_call": true, "source_file": "C:\\Users\\NITIN MISHRA\\Workspace\\01_Development\\Active\\cine-stream-platform-main.zip\\public\\js\\browse.js", "source_location": "L557"}, {"caller_nid": "js_browse_renderactivepills", "callee": "push", "is_member_call": true, "source_file": "C:\\Users\\NITIN MISHRA\\Workspace\\01_Development\\Active\\cine-stream-platform-main.zip\\public\\js\\browse.js", "source_location": "L558"}, {"caller_nid": "js_browse_renderactivepills", "callee": "push", "is_member_call": true, "source_file": "C:\\Users\\NITIN MISHRA\\Workspace\\01_Development\\Active\\cine-stream-platform-main.zip\\public\\js\\browse.js", "source_location": "L559"}, {"caller_nid": "js_browse_renderactivepills", "callee": "push", "is_member_call": true, "source_file": "C:\\Users\\NITIN MISHRA\\Workspace\\01_Development\\Active\\cine-stream-platform-main.zip\\public\\js\\browse.js", "source_location": "L560"}, {"caller_nid": "js_browse_renderactivepills", "callee": "push", "is_member_call": true, "source_file": "C:\\Users\\NITIN MISHRA\\Workspace\\01_Development\\Active\\cine-stream-platform-main.zip\\public\\js\\browse.js", "source_location": "L561"}, {"caller_nid": "js_browse_renderactivepills", "callee": "forEach", "is_member_call": true, "source_file": "C:\\Users\\NITIN MISHRA\\Workspace\\01_Development\\Active\\cine-stream-platform-main.zip\\public\\js\\browse.js", "source_location": "L562"}, {"caller_nid": "js_browse_renderactivepills", "callee": "forEach", "is_member_call": true, "source_file": "C:\\Users\\NITIN MISHRA\\Workspace\\01_Development\\Active\\cine-stream-platform-main.zip\\public\\js\\browse.js", "source_location": "L563"}, {"caller_nid": "js_browse_renderactivepills", "callee": "push", "is_member_call": true, "source_file": "C:\\Users\\NITIN MISHRA\\Workspace\\01_Development\\Active\\cine-stream-platform-main.zip\\public\\js\\browse.js", "source_location": "L565"}, {"caller_nid": "js_browse_renderactivepills", "callee": "push", "is_member_call": true, "source_file": "C:\\Users\\NITIN MISHRA\\Workspace\\01_Development\\Active\\cine-stream-platform-main.zip\\public\\js\\browse.js", "source_location": "L567"}, {"caller_nid": "js_browse_renderactivepills", "callee": "push", "is_member_call": true, "source_file": "C:\\Users\\NITIN MISHRA\\Workspace\\01_Development\\Active\\cine-stream-platform-main.zip\\public\\js\\browse.js", "source_location": "L569"}, {"caller_nid": "js_browse_renderactivepills", "callee": "join", "is_member_call": true, "source_file": "C:\\Users\\NITIN MISHRA\\Workspace\\01_Development\\Active\\cine-stream-platform-main.zip\\public\\js\\browse.js", "source_location": "L581"}, {"caller_nid": "js_browse_renderactivepills", "callee": "map", "is_member_call": true, "source_file": "C:\\Users\\NITIN MISHRA\\Workspace\\01_Development\\Active\\cine-stream-platform-main.zip\\public\\js\\browse.js", "source_location": "L581"}, {"caller_nid": "js_browse_renderactivepills", "callee": "forEach", "is_member_call": true, "source_file": "C:\\Users\\NITIN MISHRA\\Workspace\\01_Development\\Active\\cine-stream-platform-main.zip\\public\\js\\browse.js", "source_location": "L590"}, {"caller_nid": "js_browse_renderactivepills", "callee": "querySelectorAll", "is_member_call": true, "source_file": "C:\\Users\\NITIN MISHRA\\Workspace\\01_Development\\Active\\cine-stream-platform-main.zip\\public\\js\\browse.js", "source_location": "L590"}, {"caller_nid": "js_browse_renderactivepills", "callee": "addEventListener", "is_member_call": true, "source_file": "C:\\Users\\NITIN MISHRA\\Workspace\\01_Development\\Active\\cine-stream-platform-main.zip\\public\\js\\browse.js", "source_location": "L597"}, {"caller_nid": "js_browse_renderactivepills", "callee": "querySelector", "is_member_call": true, "source_file": "C:\\Users\\NITIN MISHRA\\Workspace\\01_Development\\Active\\cine-stream-platform-main.zip\\public\\js\\browse.js", "source_location": "L597"}, {"caller_nid": "js_browse_removefilter", "callee": "filter", "is_member_call": true, "source_file": "C:\\Users\\NITIN MISHRA\\Workspace\\01_Development\\Active\\cine-stream-platform-main.zip\\public\\js\\browse.js", "source_location": "L605"}, {"caller_nid": "js_browse_removefilter", "callee": "querySelector", "is_member_call": true, "source_file": "C:\\Users\\NITIN MISHRA\\Workspace\\01_Development\\Active\\cine-stream-platform-main.zip\\public\\js\\browse.js", "source_location": "L606"}, {"caller_nid": "js_browse_removefilter", "callee": "filter", "is_member_call": true, "source_file": "C:\\Users\\NITIN MISHRA\\Workspace\\01_Development\\Active\\cine-stream-platform-main.zip\\public\\js\\browse.js", "source_location": "L611"}, {"caller_nid": "js_browse_removefilter", "callee": "querySelector", "is_member_call": true, "source_file": "C:\\Users\\NITIN MISHRA\\Workspace\\01_Development\\Active\\cine-stream-platform-main.zip\\public\\js\\browse.js", "source_location": "L612"}, {"caller_nid": "js_browse_removefilter", "callee": "filter", "is_member_call": true, "source_file": "C:\\Users\\NITIN MISHRA\\Workspace\\01_Development\\Active\\cine-stream-platform-main.zip\\public\\js\\browse.js", "source_location": "L617"}, {"caller_nid": "js_browse_removefilter", "callee": "querySelector", "is_member_call": true, "source_file": "C:\\Users\\NITIN MISHRA\\Workspace\\01_Development\\Active\\cine-stream-platform-main.zip\\public\\js\\browse.js", "source_location": "L618"}, {"caller_nid": "js_browse_removefilter", "callee": "getElementById", "is_member_call": true, "source_file": "C:\\Users\\NITIN MISHRA\\Workspace\\01_Development\\Active\\cine-stream-platform-main.zip\\public\\js\\browse.js", "source_location": "L624"}, {"caller_nid": "js_browse_removefilter", "callee": "getElementById", "is_member_call": true, "source_file": "C:\\Users\\NITIN MISHRA\\Workspace\\01_Development\\Active\\cine-stream-platform-main.zip\\public\\js\\browse.js", "source_location": "L628"}, {"caller_nid": "js_browse_removefilter", "callee": "getElementById", "is_member_call": true, "source_file": "C:\\Users\\NITIN MISHRA\\Workspace\\01_Development\\Active\\cine-stream-platform-main.zip\\public\\js\\browse.js", "source_location": "L632"}, {"caller_nid": "js_browse_removefilter", "callee": "getElementById", "is_member_call": true, "source_file": "C:\\Users\\NITIN MISHRA\\Workspace\\01_Development\\Active\\cine-stream-platform-main.zip\\public\\js\\browse.js", "source_location": "L636"}, {"caller_nid": "js_browse_removefilter", "callee": "getElementById", "is_member_call": true, "source_file": "C:\\Users\\NITIN MISHRA\\Workspace\\01_Development\\Active\\cine-stream-platform-main.zip\\public\\js\\browse.js", "source_location": "L640"}, {"caller_nid": "js_browse_removefilter", "callee": "getElementById", "is_member_call": true, "source_file": "C:\\Users\\NITIN MISHRA\\Workspace\\01_Development\\Active\\cine-stream-platform-main.zip\\public\\js\\browse.js", "source_location": "L644"}, {"caller_nid": "js_browse_removefilter", "callee": "forEach", "is_member_call": true, "source_file": "C:\\Users\\NITIN MISHRA\\Workspace\\01_Development\\Active\\cine-stream-platform-main.zip\\public\\js\\browse.js", "source_location": "L648"}, {"caller_nid": "js_browse_removefilter", "callee": "querySelectorAll", "is_member_call": true, "source_file": "C:\\Users\\NITIN MISHRA\\Workspace\\01_Development\\Active\\cine-stream-platform-main.zip\\public\\js\\browse.js", "source_location": "L648"}, {"caller_nid": "js_browse_cssescape", "callee": "escape", "is_member_call": true, "source_file": "C:\\Users\\NITIN MISHRA\\Workspace\\01_Development\\Active\\cine-stream-platform-main.zip\\public\\js\\browse.js", "source_location": "L662"}, {"caller_nid": "js_browse_cssescape", "callee": "replace", "is_member_call": true, "source_file": "C:\\Users\\NITIN MISHRA\\Workspace\\01_Development\\Active\\cine-stream-platform-main.zip\\public\\js\\browse.js", "source_location": "L664"}, {"caller_nid": "js_browse_cssescape", "callee": "String", "is_member_call": false, "source_file": "C:\\Users\\NITIN MISHRA\\Workspace\\01_Development\\Active\\cine-stream-platform-main.zip\\public\\js\\browse.js", "source_location": "L664"}, {"caller_nid": "js_browse_openmobilesidebar", "callee": "getElementById", "is_member_call": true, "source_file": "C:\\Users\\NITIN MISHRA\\Workspace\\01_Development\\Active\\cine-stream-platform-main.zip\\public\\js\\browse.js", "source_location": "L673"}, {"caller_nid": "js_browse_openmobilesidebar", "callee": "getElementById", "is_member_call": true, "source_file": "C:\\Users\\NITIN MISHRA\\Workspace\\01_Development\\Active\\cine-stream-platform-main.zip\\public\\js\\browse.js", "source_location": "L674"}, {"caller_nid": "js_browse_openmobilesidebar", "callee": "getElementById", "is_member_call": true, "source_file": "C:\\Users\\NITIN MISHRA\\Workspace\\01_Development\\Active\\cine-stream-platform-main.zip\\public\\js\\browse.js", "source_location": "L675"}, {"caller_nid": "js_browse_openmobilesidebar", "callee": "add", "is_member_call": true, "source_file": "C:\\Users\\NITIN MISHRA\\Workspace\\01_Development\\Active\\cine-stream-platform-main.zip\\public\\js\\browse.js", "source_location": "L676"}, {"caller_nid": "js_browse_openmobilesidebar", "callee": "add", "is_member_call": true, "source_file": "C:\\Users\\NITIN MISHRA\\Workspace\\01_Development\\Active\\cine-stream-platform-main.zip\\public\\js\\browse.js", "source_location": "L677"}, {"caller_nid": "js_browse_openmobilesidebar", "callee": "setAttribute", "is_member_call": true, "source_file": "C:\\Users\\NITIN MISHRA\\Workspace\\01_Development\\Active\\cine-stream-platform-main.zip\\public\\js\\browse.js", "source_location": "L678"}, {"caller_nid": "js_browse_openmobilesidebar", "callee": "setItem", "is_member_call": true, "source_file": "C:\\Users\\NITIN MISHRA\\Workspace\\01_Development\\Active\\cine-stream-platform-main.zip\\public\\js\\browse.js", "source_location": "L679"}, {"caller_nid": "js_browse_closemobilesidebar", "callee": "getElementById", "is_member_call": true, "source_file": "C:\\Users\\NITIN MISHRA\\Workspace\\01_Development\\Active\\cine-stream-platform-main.zip\\public\\js\\browse.js", "source_location": "L683"}, {"caller_nid": "js_browse_closemobilesidebar", "callee": "getElementById", "is_member_call": true, "source_file": "C:\\Users\\NITIN MISHRA\\Workspace\\01_Development\\Active\\cine-stream-platform-main.zip\\public\\js\\browse.js", "source_location": "L684"}, {"caller_nid": "js_browse_closemobilesidebar", "callee": "getElementById", "is_member_call": true, "source_file": "C:\\Users\\NITIN MISHRA\\Workspace\\01_Development\\Active\\cine-stream-platform-main.zip\\public\\js\\browse.js", "source_location": "L685"}, {"caller_nid": "js_browse_closemobilesidebar", "callee": "remove", "is_member_call": true, "source_file": "C:\\Users\\NITIN MISHRA\\Workspace\\01_Development\\Active\\cine-stream-platform-main.zip\\public\\js\\browse.js", "source_location": "L686"}, {"caller_nid": "js_browse_closemobilesidebar", "callee": "remove", "is_member_call": true, "source_file": "C:\\Users\\NITIN MISHRA\\Workspace\\01_Development\\Active\\cine-stream-platform-main.zip\\public\\js\\browse.js", "source_location": "L687"}, {"caller_nid": "js_browse_closemobilesidebar", "callee": "setAttribute", "is_member_call": true, "source_file": "C:\\Users\\NITIN MISHRA\\Workspace\\01_Development\\Active\\cine-stream-platform-main.zip\\public\\js\\browse.js", "source_location": "L688"}, {"caller_nid": "js_browse_closemobilesidebar", "callee": "setItem", "is_member_call": true, "source_file": "C:\\Users\\NITIN MISHRA\\Workspace\\01_Development\\Active\\cine-stream-platform-main.zip\\public\\js\\browse.js", "source_location": "L689"}, {"caller_nid": "js_browse_setupsidebartoggle", "callee": "getElementById", "is_member_call": true, "source_file": "C:\\Users\\NITIN MISHRA\\Workspace\\01_Development\\Active\\cine-stream-platform-main.zip\\public\\js\\browse.js", "source_location": "L693"}, {"caller_nid": "js_browse_setupsidebartoggle", "callee": "getElementById", "is_member_call": true, "source_file": "C:\\Users\\NITIN MISHRA\\Workspace\\01_Development\\Active\\cine-stream-platform-main.zip\\public\\js\\browse.js", "source_location": "L694"}, {"caller_nid": "js_browse_setupsidebartoggle", "callee": "getElementById", "is_member_call": true, "source_file": "C:\\Users\\NITIN MISHRA\\Workspace\\01_Development\\Active\\cine-stream-platform-main.zip\\public\\js\\browse.js", "source_location": "L695"}, {"caller_nid": "js_browse_setupsidebartoggle", "callee": "addEventListener", "is_member_call": true, "source_file": "C:\\Users\\NITIN MISHRA\\Workspace\\01_Development\\Active\\cine-stream-platform-main.zip\\public\\js\\browse.js", "source_location": "L697"}, {"caller_nid": "js_browse_setupsidebartoggle", "callee": "addEventListener", "is_member_call": true, "source_file": "C:\\Users\\NITIN MISHRA\\Workspace\\01_Development\\Active\\cine-stream-platform-main.zip\\public\\js\\browse.js", "source_location": "L698"}, {"caller_nid": "js_browse_setupsidebartoggle", "callee": "addEventListener", "is_member_call": true, "source_file": "C:\\Users\\NITIN MISHRA\\Workspace\\01_Development\\Active\\cine-stream-platform-main.zip\\public\\js\\browse.js", "source_location": "L699"}, {"caller_nid": "js_browse_setupsidebartoggle", "callee": "getItem", "is_member_call": true, "source_file": "C:\\Users\\NITIN MISHRA\\Workspace\\01_Development\\Active\\cine-stream-platform-main.zip\\public\\js\\browse.js", "source_location": "L706"}, {"caller_nid": "js_browse_setupfilterevents", "callee": "addEventListener", "is_member_call": true, "source_file": "C:\\Users\\NITIN MISHRA\\Workspace\\01_Development\\Active\\cine-stream-platform-main.zip\\public\\js\\browse.js", "source_location": "L712"}, {"caller_nid": "js_browse_setupfilterevents", "callee": "getElementById", "is_member_call": true, "source_file": "C:\\Users\\NITIN MISHRA\\Workspace\\01_Development\\Active\\cine-stream-platform-main.zip\\public\\js\\browse.js", "source_location": "L712"}, {"caller_nid": "js_browse_setupfilterevents", "callee": "addEventListener", "is_member_call": true, "source_file": "C:\\Users\\NITIN MISHRA\\Workspace\\01_Development\\Active\\cine-stream-platform-main.zip\\public\\js\\browse.js", "source_location": "L713"}, {"caller_nid": "js_browse_setupfilterevents", "callee": "getElementById", "is_member_call": true, "source_file": "C:\\Users\\NITIN MISHRA\\Workspace\\01_Development\\Active\\cine-stream-platform-main.zip\\public\\js\\browse.js", "source_location": "L713"}, {"caller_nid": "js_browse_setupincategorysearch", "callee": "getElementById", "is_member_call": true, "source_file": "C:\\Users\\NITIN MISHRA\\Workspace\\01_Development\\Active\\cine-stream-platform-main.zip\\public\\js\\browse.js", "source_location": "L741"}, {"caller_nid": "js_browse_setupincategorysearch", "callee": "_debounce", "is_member_call": false, "source_file": "C:\\Users\\NITIN MISHRA\\Workspace\\01_Development\\Active\\cine-stream-platform-main.zip\\public\\js\\browse.js", "source_location": "L761"}, {"caller_nid": "js_browse_setupincategorysearch", "callee": "addEventListener", "is_member_call": true, "source_file": "C:\\Users\\NITIN MISHRA\\Workspace\\01_Development\\Active\\cine-stream-platform-main.zip\\public\\js\\browse.js", "source_location": "L765"}, {"caller_nid": "js_browse_setupincategorysearch", "callee": "addEventListener", "is_member_call": true, "source_file": "C:\\Users\\NITIN MISHRA\\Workspace\\01_Development\\Active\\cine-stream-platform-main.zip\\public\\js\\browse.js", "source_location": "L770"}, {"caller_nid": "js_browse_setupsubdubtoggle", "callee": "getElementById", "is_member_call": true, "source_file": "C:\\Users\\NITIN MISHRA\\Workspace\\01_Development\\Active\\cine-stream-platform-main.zip\\public\\js\\browse.js", "source_location": "L783"}, {"caller_nid": "js_browse_setupsubdubtoggle", "callee": "addEventListener", "is_member_call": true, "source_file": "C:\\Users\\NITIN MISHRA\\Workspace\\01_Development\\Active\\cine-stream-platform-main.zip\\public\\js\\browse.js", "source_location": "L790"}, {"caller_nid": "js_browse_setfilters", "callee": "assign", "is_member_call": true, "source_file": "C:\\Users\\NITIN MISHRA\\Workspace\\01_Development\\Active\\cine-stream-platform-main.zip\\public\\js\\browse.js", "source_location": "L848"}]}